Metadata-Version: 1.1
Name: tbx.aws
Version: 0.1.5
Summary: Python Toolbox Library - AWS tools. Collection of useful tools and snippets for Amazon Web Services EC2 and Route53.
Home-page: https://github.com/ronhanson/python-tbx-aws
Author: Ronan Delacroix
Author-email: ronan.delacroix@gmail.com
License: The MIT License (MIT)
